aioChatbase-1.0.0.dist-info/METADATA
aioChatbase-1.0.0.dist-info/RECORD
aioChatbase-1.0.0.dist-info/WHEEL
aioChatbase-1.0.0.dist-info/top_level.txt
aiochatbase/__init__.py
aiochatbase/chatbase.py
aiochatbase/types/__init__.py
aiochatbase/types/basic.py
aiochatbase/types/click.py
aiochatbase/types/errors.py
aiochatbase/types/event.py
aiochatbase/types/message.py
aiochatbase/types/message_types.py
aiochatbase/types/pool.py
aiochatbase/types/property.py
aiochatbase/utils/__init__.py
aiochatbase/utils/json.py
tests/__init__.py
tests/test_chatbase.py
tests/test_chatbase_pool_mode.py
tests/test_chatbase_task_mode.py
tests/test_exceptions.py
tests/test_misc.py
