Metadata-Version: 2.1
Name: aioChatbase
Version: 1.0.0
Summary: Asyncio Chatbase API library
Home-page: https://github.com/Olegt0rr/aioChatbase
Author: Oleg A.
Author-email: 1282524@gmail.com
License: UNKNOWN
Platform: UNKNOWN
Classifier: Development Status :: 5 - Production/Stable
Classifier: Environment :: Console
Classifier: Framework :: AsyncIO
Classifier: License :: OSI Approved :: MIT License
Classifier: Natural Language :: English
Classifier: Operating System :: OS Independent
Classifier: Intended Audience :: Developers
Classifier: Programming Language :: Python :: 3.6
